iterative_stats/__init__.py
iterative_stats/abstract_iterative_statistics.py
iterative_stats/experimental_design/experiment.py
iterative_stats/iterative_covariance.py
iterative_stats/iterative_dotproduct.py
iterative_stats/iterative_extrema.py
iterative_stats/iterative_mean.py
iterative_stats/iterative_moments.py
iterative_stats/iterative_quantile.py
iterative_stats/iterative_threshold.py
iterative_stats/iterative_variance.py
iterative_stats/sensitivity/__init__.py
iterative_stats/sensitivity/abstract_sensitivity.py
iterative_stats/sensitivity/sensitivity_jansen.py
iterative_stats/sensitivity/sensitivity_martinez.py
iterative_stats/sensitivity/sensitivity_saltelli.py
iterative_stats/utils/dot_prod.py
iterative_stats/utils/logger.py
iterative_stats-0.1.1.dist-info/LICENSE
iterative_stats-0.1.1.dist-info/METADATA
iterative_stats-0.1.1.dist-info/WHEEL
iterative_stats-0.1.1.dist-info/RECORD
