Metadata-Version: 2.3
Name: iterative_stats
Version: 0.1.1
Summary: This package implements iterative algorithms to compute some basics statistics
License: LICENSE
Author: Frederique Robin
Requires-Python: >=3.9,<3.13
Classifier: License :: OSI Approved :: BSD License
Classifier: License :: Other/Proprietary License
Classifier: Operating System :: OS Independent
Classifier: Programming Language :: Python :: 3
Classifier: Programming Language :: Python :: 3.9
Classifier: Programming Language :: Python :: 3.10
Classifier: Programming Language :: Python :: 3.11
Classifier: Programming Language :: Python :: 3.12
Requires-Dist: numpy (>=1.19.0,<2.0.0)
Requires-Dist: pyyaml (>=6.0)
